[{"time":"00:01.00","text":" <i>魔兽中...</i>"},{"time":"00:12.24","text":"all right,just a few more feet. And... 非常好 再前进几步..."},{"time":"00:15.44","text":"here we are,gentlemen,the gates of elzebob. 准备好 先生们 Elzebob大门到了"},{"time":"00:18.16","text":"Good lord. 上帝啊"},{"time":"00:21.32","text":"Don't panic. This is what the last 97 hours have been about. 别慌 坚持97小时的战斗就为了这一刻"},{"time":"00:22.88","text":"Stay frosty. There's a horde of armed goblins 待着别动 一群装备武器的地精"},{"time":"00:26.28","text":"on the other side of that gate guarding the sword of asaroth. 正在门的另一边 守卫着艾辛诺斯之刃"},{"time":"00:30.52","text":"Warriors,unsheathe your weapons. Magic wielders,raise your wands. 战士们 拔出你们的武器 法师们 举起你们的魔杖"},{"time":"00:32.16","text":"Lock and load. 准备好了"},{"time":"00:33.76","text":"Raj,blow the gates. Raj 推开大门"},{"time":"00:35.48","text":"Blowing the gates. 推开大门"},{"time":"00:39.80","text":"Control,shift... Control Shift..."},{"time":"00:42.80","text":"b! B!"},{"time":"00:45.64","text":"oh,my god,so many goblins! 天啊 那么多地精!"},{"time":"00:46.48","text":"Don't just stand there,slash and move,slash and move! 别傻站在那里 向前开路! 向前开路!"},{"time":"00:49.52","text":"Stay in formation! 保持阵形!"},{"time":"00:51.12","text":"Leonard,you got one on your tail. Leonard 有个敌人在你背后"},{"time":"00:53.76","text":"That's all right,my tail's prehensile- - I'll swat him off. 没事 我脑后长眼着呢 我会干掉他的"},{"time":"00:54.32","text":"I got him,leonard. 我打中他了 Leonard"},{"time":"00:56.72","text":"Tonight I spice my mead with goblin blood. 今晚我要用那地精的血来祭酒"},{"time":"00:59.80","text":"Raj,no,it's a trap! They're flanking us! Raj 不要 这是个陷阱! 他们在夹击我们!"},{"time":"01:03.68","text":"He's got me! 我被打中了!"},{"time":"01:03.60","text":"Sheldon,he's got raj. Use your sleep spell! Sheldon 他打中Raj了 快用你的催眠咒!"},{"time":"01:06.40","text":"Sheldon... sheldon? Sheldon Sheldon?"},{"time":"01:09.92","text":"I've got the sword of asaroth! 我拿到了艾辛诺斯之刃!"},{"time":"01:11.40","text":"Forget the sword,sheldon,help raj! 别管剑了 Sheldon 快救Raj!"},{"time":"01:14.88","text":"There is no more sheldon. 我不再是Sheldon了"},{"time":"01:15.40","text":"I am the sword master! 我是剑圣!"},{"time":"01:18.28","text":"Leonard,look out! Leonard 当心!"},{"time":"01:20.12","text":"Damn it,man,we're dying here! 该死 我们快不行了!"},{"time":"01:19.76","text":"Good - bye,peasants! 再见了 土人们!"},{"time":"01:24.52","text":"the bastard teleported! 那混蛋走了!"},{"time":"01:25.48","text":"He's selling the sword of asaroth on ebay. 他在ebay上出售那把艾辛诺斯之刃"},{"time":"01:29.28","text":"You betrayed us for money? Who are you? 你为了钱背叛我们? 你怎么这样?"},{"time":"01:33.04","text":"I'm a rogue night elf. Don't you people read character descriptions? 我是暗夜精灵盗贼 你们没有读过角色介绍吗?"},{"time":"01:37.60","text":"Wait,wait,wait! Somebody just clicked \"buy it now. 等等! 有人点击了\"立即购买\""},{"time":"01:38.76","text":"\" I am the sword master! 我是剑圣!"},{"time":"01:45.76","text":"Our whole universe was in a hot,dense state * 宇宙是个大火炉 *"},{"time":"01:47.64","text":"then nearly 14 billion years * 140亿年前大爆炸 哦稍等 *"},{"time":"01:50.64","text":"go expansion started... wait!"},{"time":"01:51.72","text":"The earth began to cool the autotrophs began to drool, * 地球开始冷却 生物开始繁衍 *"},{"time":"01:55.96","text":"neanderthals developed tools * 尼安得特尔人发明工具*"},{"time":"01:55.68","text":"we built the wall * 我们建造墙瓦 *"},{"time":"01:56.44","text":"we built the pyramids * 我们创造金字塔 数学 科学 历史 *"},{"time":"01:57.40","text":"math, science,history, unraveling the mystery * 揭露奥秘 *"},{"time":"01:59.32","text":"that all started with a big bang bang! * 就从宇宙大爆炸开始! *"},{"time":"02:01.84","text":"www.rrting,com"},{"time":"02:04.00","text":" 天才理论传 第一季 第3集"},{"time":"02:06.92","text":"Ooh,I'm all sweaty. Anybody want to log on to second life and go swimming? 哦 我身上都是汗 谁想再进入<第二人生>游个泳?"},{"time":"02:10.08","text":"I just built a virtual pool. 我刚建了个虚拟游泳池"},{"time":"02:14.32","text":"No. I can't look at you or your avatar right now. 不 我现在不想看见你或是你的兽身"},{"time":"02:22.80","text":"sounds like your neighbor's home. 好像是隔壁的声音"},{"time":"02:24.80","text":"Excuse me. 失陪"},{"time":"02:25.32","text":"Don't forget the mail you took accidentally on purpose 别忘了带上你\"无意\"拿到的信件"},{"time":"02:27.56","text":"so you'd have an excuse to talk to her. 这样你就有借口跟她说话了"},{"time":"02:30.32","text":"Oh,right,right,right,right. 噢 对 对"},{"time":"02:31.100","text":"Stealing snail mail- - 偷窃信箱邮件 很老套的方法 我喜欢"},{"time":"02:36.92","text":"Penny,the mailman,did it again... he... oh,sorry. Penny 邮差又... 哦 抱歉"},{"time":"02:40.32","text":"Um,oh,hi,leonard. This is doug. 嗨 Leonard 这是Doug"},{"time":"02:43.92","text":"Doug,this is my neighbor leonard. Doug 这是我邻居Leonard"},{"time":"02:43.64","text":"What's up,bro? 有事吗 老兄?"},{"time":"02:48.12","text":"Not much... 没什么..."},{"time":"02:52.68","text":"bro. 老兄"},{"time":"02:52.24","text":"Is everything okay? 一切还好吧?"},{"time":"02:54.72","text":"Yeah,no,I just... I got your mail again. Here. 是啊 我只是... 我又错拿了你的信 给你"},{"time":null,"text":""},{"time":"02:57.20","text":"Thank you. I've got to talk to that mailman. 谢谢 我得和邮差说说了"},{"time":"02:60.00","text":"Oh,no,that's probably not such a good idea. 不 这主意不怎么好"},{"time":"03:04.24","text":"You know,civil servants have a documented propensity to,you know,snap,so... 人民公仆总是非常容易...动粗"},{"time":"03:09.32","text":"okay. Well,thank you again. 好吧 还是谢谢你"},{"time":"03:11.64","text":"No problem. Bye. 没问题 再见"},{"time":"03:12.68","text":"Oh,and bye... bro. 哦 再见...老兄"},{"time":"03:23.72","text":"Penny for your thoughts. 呆呆地在想什么呢? (此谚语中正好有Penny一词)"},{"time":"03:28.84","text":"What's the matter? 怎么回事?"},{"time":"03:27.96","text":"I'm fine. Penny's fine. 我很好 Penny也很好"},{"time":"03:32.44","text":"The guy she's kissing is really fine. 和她接吻的家伙也很好"},{"time":"03:35.88","text":"Kissing,what kind of kissing? Cheeks? 接吻 哪一种? 脸颊? 嘴唇? 情人? 朋友?"},{"time":"03:38.00","text":"What is wrong with you? 你什么毛病啊?"},{"time":"03:43.64","text":"I'm a romantic. 我是个浪漫主义者"},{"time":"03:46.28","text":"Please don't tell me that your hopeless infatuation is devolving into pointless jealousy. 别告诉我你不可救药的迷恋 发展成了无意义的嫉妒"},{"time":"03:51.04","text":"I'm not jealous. I'm just a little concerned for her. 我不是嫉妒 只是有点担心她"},{"time":"03:54.52","text":"I didn't like the look of the guy that she was with. 我不怎么喜欢那家伙的长相"},{"time":"03:56.68","text":"Because he looks better than you? 因为他长得比你帅气?"},{"time":"03:57.08","text":"Yeah. 是啊"},{"time":"03:60.48","text":"He was kind of dreamy. 可以说是梦幻般的外形"},{"time":"04:04.40","text":"Well,at least now you can retrieve the black box from the twisted, 只是你现在还能从燃烧的废墟里"},{"time":"04:07.08","text":"olsmdering wreckage that was once your fantasy of dating her 找回装满对她美妙幻想的黑匣子"},{"time":"04:08.60","text":"and analyze the data so that you don't crash into geek mountain. 好好分析下数据 你就不会再坠入\"呆子谷\""},{"time":"04:15.64","text":"I di. Greesa love is not a sprint,it's a marathon- - 我反对 爱情不是短跑 而是马拉松"},{"time":"04:17.36","text":"a relentless pursuit that only ends when she falls into your arms... 永不放弃地追逐 直到她最终投入你的怀抱"},{"time":"04:22.40","text":"or hits you with the pepper spray. 或是用防狼喷雾剂喷你"},{"time":"04:28.68","text":"No,I'm done with penny. 不 我和Penny结束了"},{"time":"04:29.16","text":"I'm going to be more realistic and go after someone my own speed. 我要更现实些 去追求合我拍的人"},{"time":"04:32.40","text":"Like who? 比如谁?"},{"time":"04:34.20","text":"I don't know... olivia geiger. 不知道... Olivia Geiger"},{"time":"04:34.60","text":"The dietician at the cafeteria with the limp and the lazy eye? 自助餐厅里那个有点跛 还有弱视的营养学家?"},{"time":"04:41.28","text":"Yeah. 是的"},{"time":"04:42.08","text":"Oh,I don't think you have a shot there. 哦 我看你没戏"},{"time":"04:45.48","text":"I have noticed that leslie winkle recently started shaving her legs. 我注意到Leslie Winkle 最近在刮她的腿毛"},{"time":"04:49.76","text":"Now given that winter is coming, 既然冬天都已经到了"},{"time":"04:50.48","text":"one can only assume she's signaling sexual availability. 只能说明她是在暗示 她可以作为做爱对象"},{"time":"04:53.12","text":"I don't know. You guys work in the same lab. 我不清楚 你们在同一个实验室"},{"time":"04:55.72","text":"So? 所以呢?"},{"time":"04:56.56","text":"There are pitfalls. Trust me,I know. 这有隐患 相信我 我清楚"},{"time":"04:60.04","text":"When it comes to sexual harassment law,I'm a bit of a self taught expert. 说到性骚扰的相关法律 我可是自学而成的专家"},{"time":"05:07.64","text":"Look,howard,if I were to ask leslie winkle out,it would just be for dinner. Howard 如果我要约Leslie Winkle出去 也只是吃顿饭"},{"time":"05:11.84","text":"I'm not going to walk into the lab,ask her to strip naked and dance for me. 我不会去实验室 要她为我跳脱衣舞"},{"time":"05:16.52","text":"Oh,then you're probably okay. 哦 那你就没事了"},{"time":"05:22.48","text":"Hello,leslie. 嗨 Leslie"},{"time":"05:23.80","text":"Hi,leonard. 嗨 Leonard"},{"time":"05:22.36","text":"Leslie,I would like to propose an experiment... Leslie 我建议做个实验..."},{"time":"05:25.04","text":"- goggles,leonard. - Right. - 戴上眼镜 Leonard - 好吧"},{"time":"05:29.52","text":"Leslie,I would like p toropose an experiment. Leslie 我建议做个实验"},{"time":"05:30.72","text":"Hang on. 等一下"},{"time":"05:32.52","text":"I'm trying to see how long it takes a 500 - kilowatt oxygen iodine laser 我想试试一个500千瓦氧碘激光器"},{"time":"05:35.72","text":"to heat up my cup a' noodles. 得花多久把我的杯装泡面加热"},{"time":"05:39.16","text":"I've done it. About two seconds. 2. 6 for minestrone. 我试过 大概2秒 蔬菜汤花2.6秒"},{"time":"05:47.72","text":"anyway,I was thinking more of a bio- social exploration with a neuro- chemical overlay. 总之 我在考虑来个生物学的社交探索 结合神经化学方面的专家知识"},{"time":"05:54.28","text":"Wait,are you asking me out? 等等 你约我出去?"},{"time":"05:58.96","text":"I was going to characterize it as the modification of our colleague- slash- friendship paradigm 我认为是改变我们 同事/友谊关系的范例"},{"time":null,"text":""},{"time":"06:03.08","text":"with the addition of a date like component, 外加个约会作为补充成分"},{"time":"06:04.64","text":"but we don't need to quibble over terminology. 但我们不需要一直说术语"},{"time":"06:09.32","text":"What sort of experiment would you propose? 你计划做怎样的实验?"},{"time":"06:10.48","text":"There's a generally accepted pattern in this area. 这个领域有种普遍接受的模式"},{"time":"06:13.60","text":"I would pick you up,take you to a restaurant. 我去接你 带你去餐厅"},{"time":"06:17.12","text":"Then we would see a movie, 接着我们可以看场电影"},{"time":"06:18.04","text":"probably a romantic comedy featuring the talents of hugh grant or sandra bullock. 也许一部休·格兰特或桑德拉·布洛克 天才演绎的浪漫轻喜剧"},{"time":"06:24.40","text":"Interesting. 有意思"},{"time":"06:25.68","text":"And would you agree that the primary way we would evaluate 你是否同意 我们评价约会成败的依据"},{"time":"06:28.00","text":"either the success or failure of the date would be based 是基于离别之吻时的化学反应?"},{"time":"06:28.56","text":"on the biochemical reaction during the good night kiss?"},{"time":"06:32.72","text":"Heart rate,pheromones,etc. Yes. 心跳率 生化信息素等等 的确"},{"time":"06:35.60","text":"Why don't we just stipulate that the date goes well and move to the key variable? 我们干嘛不假定约会很顺利 直接进行关键的有变数的部分?"},{"time":"06:39.76","text":"You mean kiss you now? 你意思是现在就吻你?"},{"time":"06:41.00","text":"Yes. 是的"},{"time":"06:41.88","text":"Can you define the parameters of the kiss? 你怎么定义吻的参数吗?"},{"time":"06:42.72","text":"Close - mouthed but romantic. Mint? 嘴唇的亲密度还有浪漫度 要薄荷吗?"},{"time":"06:44.12","text":"Thank you. 谢谢"},{"time":"06:54.84","text":"shall I count down from three? 我数三下?"},{"time":"06:53.20","text":"No,I think it needs to be spontaneous. 不 我觉得应该自然点"},{"time":"07:05.32","text":"What do you think? 感觉怎么样?"},{"time":"07:06.16","text":"You proposed the experiment. I think you should present your findings first. 你提出的实验方案 该由你先说说实验的发现"},{"time":"07:10.12","text":"Fair enough. 很公平"},{"time":"07:10.88","text":"On the plus side,it was a good kiss. 从正面讲 这个吻很不错"},{"time":"07:14.40","text":"Reasonable technique,no extraneous spittle. 合理的技术 没有多余的唾沫"},{"time":"07:18.72","text":"On the other hand,no arousal. 另一方面讲 没什么感觉"},{"time":"07:19.52","text":"- None? - None. - 没感觉? - 没有"},{"time":"07:25.48","text":"Well,thank you for your time. 呃 很感谢你抽出时间"},{"time":"07:28.56","text":"Thanyok U. 谢谢你"},{"time":"07:33.32","text":"None at all? 一点感觉都没?"},{"time":"07:38.64","text":"Sheldon,if you were a robot,and I knew and you didn'T... ... Sheldon 如果你是机器人 我知道但你自己不知道..."},{"time":"07:48.12","text":"would you want me to tell you? 你希望我告诉你吗?"},{"time":"07:49.64","text":"That depends. 看情况"},{"time":"07:53.76","text":"When I learn that I'm a robot... 当我得知我是机器人..."},{"time":"07:55.88","text":"will I be able to handle it? 我有能力承受吗?"},{"time":"07:60.72","text":"Maybe- - although the history of science fiction is not on your side. 也许吧 虽然历来的科幻小说 都不能苟同这点"},{"time":"08:04.00","text":"Okay,uh,let me ask you this- - 好吧 我来问你"},{"time":"08:07.00","text":"when I learn that I'm a robot, 当我得知我是机器人"},{"time":"08:09.92","text":"would I be bound by asimov's three laws of robotics? 我要受限于阿西莫夫的\"机器人三定律\"吗?"},{"time":"08:12.24","text":"You might be bound by them right now. 你可能现在就受限哦"},{"time":"08:20.96","text":"That's true. 就是啊"},{"time":"08:19.56","text":"Have you ever harmed a human being 你伤害过人类吗?"},{"time":"08:21.76","text":"or through inaction allowed a human being to come to harm? 或任人受伤而袖手旁观?"},{"time":"08:24.80","text":"Of course not. 当然没有"},{"time":"08:24.88","text":"Have you ever harmed yourself or allowed yourself to be harmed except in cases 除非在他人危险的情况下 你会伤害自己"},{"time":"08:26.80","text":"where a human being would have been endangered? 或容忍自己被伤害吗?"},{"time":"08:31.48","text":"Well,no. 呃 没有"},{"time":"08:32.48","text":"I smell robot. 我闻到机器人的味道了 (以上问题均出自\"机器人三定律\")"},{"time":"08:35.96","text":"Hey,what's going on? 嘿 过得怎么样?"},{"time":"08:37.56","text":"Internet's been down for half an hour. 互联网瘫痪半个小时了"},{"time":"08:43.76","text":"Also,sheldon may be a robot. 还有 Sheldon可能是机器人"},{"time":"08:45.12","text":"So how'd it go with leslie? 和Leslie怎么样啦?"},{"time":"08:50.40","text":"Oh,we tried kissing,but the earth didn't move. 哦 我们试着接吻 但地球没转"},{"time":"08:53.24","text":"I mean,any more than the 383 miles that it was going to move anyway. 我是说 比地球原来转的383英里要更多"},{"time":"08:60.00","text":"Oh,I've seen that look before. 哦 我以前看过他这表情"},{"time":"09:02.08","text":"This is just going to be two weeks of moping 未来两周 他将不停地拖地"},{"time":"09:04.96","text":"and tedious emo songs 哼唱乏味的情感核歌曲"},{"time":"09:05.44","text":"and calling me to come down to pet stores to look at cats. 要我下去宠物商店看猫"},{"time":"09:11.96","text":"I don't know if I can take it. 我不知道撑不撑得住"},{"time":null,"text":""},{"time":"09:13.08","text":"You could power down. 你可以关掉自己的电源"},{"time":"09:18.00","text":"Well,as usual,wolowitz has the solution. 一如既往 Wolowitz会有解决办法的"},{"time":"09:23.52","text":"I happen to know a place where there are plenty of eligible women 我碰巧知道个好地方 有很多符合条件的女士"},{"time":"09:25.32","text":"and leonard could have his pick. Leonard可以任意选"},{"time":"09:36.12","text":"remember the latin hips. 记住拉丁舞的技巧"},{"time":"09:38.44","text":"Shoulders stay still,and... we sway. 肩膀挺直 然后摇摆"},{"time":"09:47.04","text":"One,two,three... ... 一 二 三..."},{"time":"09:50.08","text":"five,six,seven. 五 六 七"},{"time":"09:52.08","text":"I think mrs. Tishman's got her eye on you. Tishman女士一直盯着你呢"},{"time":"09:56.88","text":"I've been there. You're in for a treat. 我有过经验 你会喜欢的"},{"time":"10:04.68","text":"She said,\"you don't know me\" \"她说 你不了解我\""},{"time":"10:08.44","text":"doyou \"n't even care\" \"你甚至不在乎\""},{"time":"10:14.40","text":"oh,yeah... \"哦 耶\""},{"time":"10:15.96","text":"oh,good lord. 哦 上帝"},{"time":"10:17.76","text":"She said,\"you don't know me\" \"她说 你不了解我\""},{"time":"10:19.24","text":"\"you don't wear my chains\" \"你不戴我送你的项链\""},{"time":"10:25.00","text":"oh,yeah. God,that's a good song. \"哦 耶\" 天啊 这歌真棒"},{"time":"10:31.84","text":"If you're compiling a mix cd for a double suicide. 当然 如果这是你为双重自杀混合录制的CD"},{"time":"10:35.28","text":"Oh,I hope that scratching post is for you. 我希望那\"猫抓柱\"是你自己用的"},{"time":"10:38.24","text":"I know what you're thinking. I've taken your asthma into account. 我知道你在想什么 你的哮喘病我有考虑在内"},{"time":"10:41.52","text":"There's a feline geneticist in san diego 圣地亚哥有个研究猫科的遗传学家"},{"time":"10:44.28","text":"who's developed the cutest little hypoallergenic calicos. 培育了一种超可爱的低变应原小猫"},{"time":"10:47.60","text":"Leonard,listen to me... Leonard 听我说..."},{"time":"10:48.56","text":"I've been thinking about names. 我在想给它起什么名字"},{"time":"10:47.12","text":"I'm kind of torn between einstein,newton and sergeant fuzzy boots. 在爱因斯坦 牛顿和毛靴中士之间犹豫"},{"time":"10:52.44","text":"Leonard,do you really think you can satisfy your need Leonard 你真认为养一只转基因猫"},{"time":"10:54.20","text":"for a relationshh witip a genetically altered cat? 可以满足你的感情需要吗?"},{"time":"10:58.84","text":"Maybe. 也许"},{"time":"10:60.64","text":"If it's a cute,little,cuddly cat. 一只让人爱不释手的可爱小猫"},{"time":"11:02.04","text":"Oh,come on. Leonard... 得了吧 Leonard..."},{"time":"11:07.84","text":"this is obviously about penny. 这都是因为Penny吧"},{"time":"11:10.28","text":"It doesn't matter. 没所谓"},{"time":"11:12.60","text":"The woman's not interested in me. The woman rejected me. 她对我不感兴趣 拒绝了我"},{"time":"11:15.20","text":"Okay,look,I think that you have as much of a chance of having a sexual relationship with penny 听着 我认为你能跟Penny做爱的几率"},{"time":"11:21.92","text":"as the hubble telescope does of discovering at the center of every black hole is a little man 跟哈勃太空望远镜发现在每个黑洞中央"},{"time":"11:26.56","text":"with a flashlight searching for a circuit breaker. 都有个小人在用闪光灯 寻找断路器的几率一样大"},{"time":"11:33.32","text":"Nevertheless, 尽管如此"},{"time":"11:35.16","text":"I do feel obligated to point out to you that she did not reject you. 我还是有责任向你指出 她并没有拒绝你"},{"time":"11:39.72","text":"You did not ask her out. 你从没邀请她去约会"},{"time":"11:43.88","text":"You're right. 你说的对"},{"time":"11:44.40","text":"I didn't ask her out. I should ask her out. 我没请她约会过 我该去请她约会"},{"time":"11:46.48","text":"No,no,now that was not my point. 不不不 重点不是这个"},{"time":"11:49.16","text":"My point was don't buy a cat. 重点是 不要养猫"},{"time":"11:51.92","text":"No,but you're right. 不 你是对的"},{"time":"11:54.04","text":"I should march over there and ask her out. 我该过去请她约会"},{"time":"11:56.68","text":"Oh,goody,we're getting a cat. 天 我们要养猫了"},{"time":"12:01.48","text":"Uh... no. 啊...不"},{"time":"12:06.96","text":"Oh,hey,leonard. 你好 Leonard"},{"time":"12:07.60","text":"Good afternoon,penny. So,hi... hey. 下午好 Penny 嗨 你好"},{"time":"12:11.92","text":"Uh... 呃..."},{"time":"12:12.32","text":"I was wondering if you had plans for dinner. 你约了人吃饭吗?"},{"time":"12:14.24","text":"Uh,you mean dinner tonight? 今晚的饭?"},{"time":"12:19.80","text":"There is an inherent ambiguity in the word \"dinner. \"饭\"这个词本身就意思含糊"},{"time":"12:20.28","text":"\" Technically it refers to the largest meal of the day whenever it's consumed. 严格说来它所指的是一日的主餐 可以是午餐或晚餐"},{"time":"12:25.32","text":"So to clarify here,by dinner I mean supper. 为了说清楚 我指的是晚饭"},{"time":"12:26.68","text":"- Supper? - Or dinner. - 晚饭? - 就是吃饭啦"},{"time":"12:30.80","text":"I was thinking 6:30 if you can go. Or a different time. 如果你有空 6点半行吗? 或者其他你方便的时间"},{"time":"12:32.48","text":"Uh,6:30's great. 6点半可以啊"},{"time":"12:35.88","text":"Really? 真的?"},{"time":"12:36.80","text":"Great. 太好了"},{"time":"12:39.92","text":"Yeah,I like hanging out with you guys. 我喜欢跟你们一起玩"},{"time":null,"text":""},{"time":"12:40.60","text":"Us guys? 我们?"},{"time":"12:41.96","text":"Yeah,you know,sheldon,howard,raj. Who all's coming? 对 Sheldon Howard Raj 他们都一起吧?"},{"time":"12:46.12","text":"They... might all be there. 他们...可能都会去吧"},{"time":"12:50.56","text":"Or a subset of them might be there. 或者他们中的有些人可能去"},{"time":"12:54.76","text":"Algebraically speaking,there are too many unknowns. 从代数角度看 太多未知数了"},{"time":"12:56.24","text":"For example,sheldon had quiznos for lunch. 比如 Sheldon中午吃了Quizno三明治"},{"time":"12:59.20","text":"Sometimes he finds that filling,other times he doesn'T. 有时他觉得吃那个饱 有时候不觉得"},{"time":"12:60.04","text":"It's no fault of quiznos- - they have a varied menu. 这不是店家的错 他们的菜单很丰盛"},{"time":"13:05.48","text":"Okay,whatever. It sounds like fun. 好吧 无所谓啦 听起来挺有意思的"},{"time":"13:09.48","text":"Great. Did we say a time? 很好 我们约时间了吗?"},{"time":"13:10.28","text":"6:30. 6点半"},{"time":"13:10.72","text":"- And that's still good for you? - It's fine. - 你确定那时有空? - 对"},{"time":"13:14.92","text":"- 'Cause it's not carved in stone. - No,6:30's great. - 不是刻在石板上非得那时去哦 - 6点半正好"},{"time":"13:16.76","text":"I'll get my chisel. 我去拿凿子"},{"time":"13:20.08","text":"Why? 为什么?"},{"time":"13:22.28","text":"To... carve the... I'll see you at 6:30. 去刻在石...6点半见"},{"time":"13:36.28","text":"How do I look? 我看起来如何?"},{"time":"13:43.40","text":"Could you be more specific? 你能说具体一点吗?"},{"time":"13:48.68","text":"Can you tell I'm perspiring a little? 能看出来我在冒汗吗?"},{"time":"13:49.44","text":"No. 不能"},{"time":"13:50.72","text":"The dark crescent shaped patterns under your arms conceal it nicely. 你腋下深色的新月状图案 将其隐藏的很好"},{"time":"13:58.08","text":"What time is your date? 你几点约会?"},{"time":"13:59.44","text":"6:30. 6点半"},{"time":"13:60.36","text":"Perfect. That gives you two hours and 15 minutes for 太好了 那你还有2小时15分"},{"time":"14:02.68","text":"that dense molecular cloud of aramis to dissipate. 让那片稠密的人造纤维分子云消散"},{"time":"14:06.20","text":"Is it too much? 汗很多吗?"},{"time":"14:07.72","text":"Not if you're a rugby team. 如果你是橄榄球队员就不算多"},{"time":"14:10.92","text":"By the way,if it should ever come up,you didn't join us 如果以后提到今晚的事 你没来参加的原因是"},{"time":"14:13.92","text":"because you stuffed yourself with a chicken carbonara sub at quiznos. 你在Quiznos吃鸡肉三明治吃撑了"},{"time":"14:16.44","text":"Why would I join you? 我为什么要去参加?"},{"time":"14:18.96","text":"No reason. 不为什么"},{"time":"14:22.52","text":"Oh,you know what,maybe this isn't such a good idea. 你知道吗 也许这样做不好"},{"time":"14:26.68","text":"Oh,no,well,now there's always the possibility that alcohol and poor judgment 不 酒精加上她一时糊涂"},{"time":"14:29.44","text":"on her part might lead to a nice romantic evening. 总有可能让今晚成为浪漫之夜"},{"time":"14:35.28","text":"You're right. Alcohol,poor judgment- - it could go well. 你说的对 酒 糊涂 今晚有可能会顺利的"},{"time":"14:37.60","text":"Of course there is the other possibility, 当然还有另一种可能性"},{"time":"14:38.00","text":"that this date kicks off a rather unpleasant six months 之后的6个月都会很难捱"},{"time":"14:42.92","text":"of the two of you passing awkwardly in the hall, 俩人在走廊里尴尬的擦身而过"},{"time":"14:43.92","text":"until one of you breaks down and moves to another zip code. 直到其中一人崩溃并搬到别的州去"},{"time":"14:48.32","text":"You could've stopped at \"it could go well. 你说到\"可能会顺利\"就可以闭嘴了"},{"time":"14:50.64","text":"\" If I could've,I would've. \"如果我能 我会的\""},{"time":"14:53.72","text":"I mean,I'm a perfectly nice guy. 我是绝种好男人"},{"time":"14:57.36","text":"There's no reason we couldn't go to the restaurant,and have a lovely dinner, 没理由我们不能 在餐厅吃好顿晚餐"},{"time":"14:58.40","text":"maybe take a walk afterwards,talk about things we have in common. 饭后散散步 聊些共同话题"},{"time":"15:04.44","text":"You love pottery? I love pottery! \"你喜欢陶艺? 我超爱陶艺的!\""},{"time":"15:06.96","text":"There's a pause,we both know what's happening. 然后暂停一下 我们都知道接下来要发生什么"},{"time":"15:09.04","text":"I lean in,we kiss. 我倾身向前 我俩接吻"},{"time":"15:10.24","text":"It's a little tentative at first,but then I realize she's kissing me back. 开始时还有点犹豫 然后她开始回吻我"},{"time":"15:13.00","text":"She's biting my lower lip! She wants me! 她在咬我的下唇! 她想要我!"},{"time":"15:16.12","text":"This thing is going the distance! We're going to have sex! 这事能成!我们会做爱!"},{"time":"15:18.36","text":"Oh,god,oh,my god! 天 上帝啊!"},{"time":"15:22.56","text":"Is the sex starting now? 现在开始做爱了?"},{"time":"15:27.28","text":"I'm having a panic attack. 我恐慌症发作了"},{"time":"15:26.32","text":"Oh,okay. Uh,well then... calm down. 好吧 冷静点"},{"time":"15:31.96","text":"If I could calm down,I wobe having a panic att... that's why they call it a panic attack. 如果我能冷静 就不会恐慌了! 不然这怎么叫做恐慌症发作!"},{"time":"15:34.40","text":"All right,all right. Uh,s- s- sit down. 好好 你坐下"},{"time":null,"text":""},{"time":"15:36.28","text":"Yeah,sit down. Now close your eyes. 坐下 闭上眼"},{"time":"15:38.92","text":"- Why? - Just do it. - 为什么? - 照做吧!"},{"time":"15:40.56","text":"Okay. 好"},{"time":"15:40.40","text":"Now try to increase your alpha wave activity. 试着增加你α波的活性 (α波是脑电图中最著名的一种波 在正常成年人闭眼放松时产生)"},{"time":"15:44.56","text":"What? ! 什么? !"},{"time":"15:45.08","text":"It's a biofeedback technique. 这是机能反馈疗法"},{"time":"15:47.76","text":"It's relaxation through brain wave manipulation. 通过控制脑电波来放松"},{"time":"15:49.12","text":"I read a paper about it in journal of american neuroscience. 我在美国神经科学月刊上 看到一篇关于它的论文"},{"time":"15:51.32","text":"It was a little sparsely sourced,but I think the basic science is valid. 它的理论来源不完备 但是我认为基本原理正确"},{"time":"15:56.56","text":"I probably have it here somewher E. 我可能把它放在这了"},{"time":"15:58.36","text":"Who am I kidding? I can't go through with this. 我没法赴这个约会"},{"time":"15:59.44","text":"You need to call her and cancel. 你给她打电话取消吧"},{"time":"16:02.76","text":"- Me? - Yes. - 我? - 对"},{"time":"16:04.24","text":"- What should I tell her? - I don't know. - 我要跟她说什么? - 我不知道"},{"time":"16:03.28","text":"- Tell her I'm sick. - Okay. - 跟她说我病了 - 好"},{"time":"16:07.24","text":"Not the kind of illness that will make her want to come over and take care of me, 别说那种会让她想来照顾我的病"},{"time":"16:08.92","text":"but nothing so critical that she'll feel uncomfortable going out with me in the future 也不要严重得让她 以后不愿跟我约会的病"},{"time":"16:11.28","text":"if I want to try this again. 如果我以后还想尝试的话"},{"time":"16:12.60","text":"Got it. 了解"},{"time":"16:14.20","text":"So I'm assuming nothing venereal? 那不能说花柳病啦?"},{"time":"16:20.84","text":"I'll just tell her that you had a routine conoloscopy and haven't quite bounced back. 就跟她说你做了例行肠镜检查 还没恢复吧"},{"time":"16:25.24","text":"Give me the phone. 给我电话"},{"time":"16:26.28","text":"I thought you wanted to cancel. 你不是想取消约会吗?"},{"time":"16:28.44","text":"I can't,because if I don't show up she'll still be expecting you. 不行 如果我不出现 她还是会认为你会去的"},{"time":"16:30.52","text":"Why would she be expecting me? 为什么她认为我会去?"},{"time":"16:35.96","text":"Stop asking me all these questions. I need to take another shower. 别问了 我要再去洗个澡"},{"time":"16:41.08","text":"So are the rest of the guys meeting us here? 其他的人直接来这找我们?"},{"time":"16:42.12","text":"Oh,yeah... no. 对...不对"},{"time":"16:45.00","text":"It turns out that raj and howard had to work,and sheldon... Raj跟Howard要工作 Sheldon..."},{"time":"16:51.16","text":"had a colonoscopy and he hasn't quite bounced back yet. 做了肠镜 还没恢复过来"},{"time":"16:54.32","text":"Oh,my uncle just had a colonoscopy. 我叔叔也做了肠镜"},{"time":"16:56.60","text":"You're kidding. Then that's something we have in common. 这就是我们俩的共同之处了"},{"time":"17:02.92","text":"How? 怎么说?"},{"time":"17:03.68","text":"We both have people in our lives who... 我们都认识..."},{"time":"17:06.80","text":"want to nip intestinal polyps in the bud. 想将肠道息肉扼杀于摇篮当中的人"},{"time":"17:17.84","text":"so what's new in the world of physics? 物理界有啥新闻不?"},{"time":"17:18.76","text":"Nothing. 没有"},{"time":"17:22.96","text":"Really? Nothing? 真的? 一点都没有?"},{"time":"17:23.16","text":"Well,with the exception of string theory, not much has happened since the 1930s. 除了弦理论 自1930年后就没什么发现了"},{"time":"17:30.88","text":"And you can't prove string theory. 而弦理论也尚未证明"},{"time":"17:32.56","text":"At best you can say,\"hey,look, 最多就能说"},{"time":"17:33.64","text":"my idea has an internal logical consistency. \"嘿 我的理论内部逻辑很连贯\""},{"time":"17:37.68","text":"\" Ah. 啊"},{"time":"17:40.44","text":"Well,I'm sure things will pick up. 我相信情况会好转的"},{"time":"17:45.20","text":"What's new at the cheesecake factory? 芝士蛋糕工厂那边有什么新消息?"},{"time":"17:48.04","text":"Oh,uh,not much. 没有什么"},{"time":"17:49.20","text":"We do have a chocolate key lime that's moving pretty well. 有个巧克力柠檬派卖得很好"},{"time":"17:55.60","text":"Good. Good. 很好"},{"time":"18:02.88","text":"What about your,uh... 那你那个..."},{"time":"18:04.08","text":"hallway friend? 过道上的朋友怎样?"},{"time":"18:05.36","text":"Doug? Oh,yeah,I don't know. Doug? 我不知道"},{"time":"18:09.52","text":"I mean,you know,he's nice and funny,but... 他人挺好也很风趣 但是..."},{"time":"18:09.00","text":"can I get you started with some drinks? 准备开始点饮品了吗?"},{"time":"18:10.04","text":"No! 不!"},{"time":"18:14.12","text":"- You were saying? But... - I'd like a drink. - 你刚刚说到? 但是... - 我想喝点东西"},{"time":"18:16.00","text":"Just say the \"but\" thing about doug and then I'll get her back. 先说完关于Doug的\"但是\" 我会把她叫回来"},{"time":"18:20.24","text":"Okay,well,I don't know,it's just me. 我不知道 是我的问题"},{"time":"18:23.52","text":"I'm still getting over this breakup with kurt 我还没从跟Kurt的分手中完全恢复"},{"time":"18:24.28","text":"and this thing with doug would stju be rebound sex. 跟Doug在一起是为了复健性爱"},{"time":null,"text":""},{"time":"18:28.16","text":"Oh,don't get me started on rebound sex. 噢 提起复健性爱啊..."},{"time":"18:34.56","text":"It's just... it's my pattern. 我总是这样"},{"time":"18:35.08","text":"I break up,then I find some cute guy, 分手后找个帅哥"},{"time":"18:38.68","text":"and then it's just 36 meaningless hours of... 然后就是36小时毫无意义的..."},{"time":"18:42.40","text":"you know. 你知道"},{"time":"18:43.04","text":"I'm not sure that I do. 我不确定我知道"},{"time":"18:48.84","text":"is that one 36-hour experience, 是连续36个小时"},{"time":"18:49.84","text":"or is that 36 hours spread out over,say... 还是一个辉煌夏季中..."},{"time":"18:54.20","text":"one glorious summer? 分散的36个小时?"},{"time":"18:55.12","text":"No,it's usually over a weekend, 不 大概是一个周末吧"},{"time":"18:56.24","text":"and trust me,you do not feel good after it. 相信我 那之后感觉很不好"},{"time":"18:59.88","text":"Well,chafing,right? 呃 皮肤疼痛是吧?"},{"time":"19:04.64","text":"Emotionally. 心情不好"},{"time":"19:05.88","text":"Of course,yeah,emotional chafing. 没错 心里疼痛"},{"time":"19:16.28","text":"Hey,do you want to see something cool? 你想看些有趣的玩意吗?"},{"time":"19:17.100","text":"I can make this olive go into this glass without touching it. 我不用手碰 就能把这颗橄榄弄进杯子里"},{"time":"19:24.96","text":"- How? - Physics. - 怎么弄啊? - 物理原理"},{"time":"19:32.60","text":"Wow,centrifugal force. 哇 离心力"},{"time":"19:32.32","text":"Actually,it's centripetal force, 实际上 是向心力"},{"time":"19:35.68","text":"which is an inward force generated by the glass acting on the olive... 玻璃对橄榄作用产生的内向力"},{"time":"19:42.40","text":"Excuse me. 抱歉"},{"time":"19:42.36","text":"If you were riding on the olive, 如果你坐在那颗橄榄上"},{"time":"19:45.48","text":"you'd be in a non - inertial reference frame and would... 你就是一个非惯性参照系 并会..."},{"time":"19:51.28","text":"are you okay? 你没事吧?"},{"time":"19:52.08","text":"Yeah,I'm okay. 没事"},{"time":"19:54.52","text":"Did you spill ketchup? 你打翻花生酱了吗?"},{"time":"19:55.28","text":"- No. - I'm not okay. - 没 - 那有事了"},{"time":"20:03.76","text":"Are you sure you don't want to go to the emergency room? 你确定不用去急诊室?"},{"time":"20:05.56","text":"No,no,I'm okay. It stopped bleeding. 我没事 不流血了"},{"time":"20:08.44","text":"I know,but you did throw up. Isn't that a sign of a concussion? 但你吐了啊 那不是脑震荡的症状吗?"},{"time":"20:11.12","text":"Yes. But I get car sick,too,so... 对 但我也晕车 所以..."},{"time":"20:13.64","text":"okay. 好吧"},{"time":"20:16.32","text":"Sorry about your car,by the way. 还有 抱歉弄脏你的车"},{"time":"20:16.96","text":"Oh,no,it's fine. You got most of it out the window. 没关系 大部分你都吐车外了"},{"time":"20:21.72","text":"The poor guy on the bike. 那个骑自行车的可怜人"},{"time":"20:25.00","text":"Well,I had a nice time. 我今晚过得很愉快"},{"time":"20:27.96","text":"Yeah,me,too. 我也是"},{"time":"20:29.92","text":"Well,um,good night. 那晚安啦"},{"time":"20:31.80","text":"Good night. 晚安"},{"time":"20:35.48","text":"- Leonard? - Ahye? - Leonard? - 啊?"},{"time":"20:36.00","text":"Was this supposed to be a date? 今晚这是约会吗?"},{"time":"20:39.04","text":"This? 今晚?"},{"time":"20:42.20","text":"No. 不是"},{"time":"20:44.88","text":"No,of course not. 当然不是"},{"time":"20:47.32","text":"This was just you and me hanging out with a bunch of guys 只是你跟我还有一帮"},{"time":"20:48.100","text":"who didn't show up 'cause of work and a colonoscopy. 因工作和肠镜而没有出现的人的聚会"},{"time":"20:56.36","text":"Okay,I was just checking. 好 我只是问问"},{"time":"20:57.20","text":"When I take a girl on a date- - and I do- - 如果我跟女孩约会 我确实跟女孩约会"},{"time":"21:03.96","text":"she knows she's been dated. 那个女孩会知道她是在约会的"},{"time":"21:07.56","text":"Capital D. 大写D"},{"time":"21:08.08","text":"boldface. Undeinrled. 粗体黑字 下划线 (在强调会让对方意识到是约会= =)"},{"time":"21:10.44","text":"Da... ted. <i><b><u>约 会</u></b></i>"},{"time":"21:15.36","text":"I think I might have a little concussion. I'm gonna go lie down. 我可能脑震荡了 我去躺躺"},{"time":"21:17.92","text":"Good night. 晚安"},{"time":"21:23.84","text":"So,how was your date? 约会如何?"},{"time":"21:26.08","text":"Awesome! 赞!"},{"time":"21:29.100","text":"Score one for liquor and poor judgment. 凭酒跟糊涂得一分"},{"time":null,"text":""},{"time":null,"text":""},{"time":null,"text":""},{"time":null,"text":""},{"time":null,"text":""},{"time":null,"text":""}]